time_helper/__init__.py
time_helper/const.py
time_helper/convert.py
time_helper/dst.py
time_helper/natural.py
time_helper/ops.py
time_helper/range.py
time_helper/timezone.py
time_helper/wrapper.py
time_helper-0.3.0.dist-info/METADATA
time_helper-0.3.0.dist-info/WHEEL
time_helper-0.3.0.dist-info/licenses/LICENSE
time_helper-0.3.0.dist-info/RECORD
