Metadata-Version: 2.4
Name: time-helper
Version: 0.3.0
Summary: A Python time helper library
Project-URL: Homepage, https://github.com/felixnext/python-time-helper
Project-URL: Repository, https://github.com/felixnext/python-time-helper
Project-URL: Issues, https://github.com/felixnext/python-time-helper/issues
Author: Felix Geilert
Maintainer: Felix Geilert
License: MIT License
License-File: LICENSE
Keywords: datetime,helper,time,timezone
Classifier: Development Status :: 4 - Beta
Classifier: Intended Audience :: Developers
Classifier: License :: OSI Approved :: MIT License
Classifier: Operating System :: OS Independent
Classifier: Programming Language :: Python :: 3
Classifier: Programming Language :: Python :: 3.10
Classifier: Programming Language :: Python :: 3.11
Classifier: Programming Language :: Python :: 3.12
Classifier: Programming Language :: Python :: 3.13
Classifier: Topic :: Software Development :: Libraries :: Python Modules
Requires-Python: >=3.10
Requires-Dist: python-dateutil>=2.8.2
Requires-Dist: pytz>=2022.1
Requires-Dist: tzdata>=2022.1
Provides-Extra: numpy
Requires-Dist: numpy>=1.22.3; extra == 'numpy'
Provides-Extra: pandas
Requires-Dist: pandas>=1.4.1; extra == 'pandas'
